LICENSE
MANIFEST.in
Makefile
README
setup.cfg
setup.py
test/test_compile.py
test/test_instance.py
tiddlywebplugins/__init__.py
tiddlywebplugins/imaker.py
tiddlywebplugins.imaker.egg-info/PKG-INFO
tiddlywebplugins.imaker.egg-info/SOURCES.txt
tiddlywebplugins.imaker.egg-info/dependency_links.txt
tiddlywebplugins.imaker.egg-info/namespace_packages.txt
tiddlywebplugins.imaker.egg-info/not-zip-safe
tiddlywebplugins.imaker.egg-info/requires.txt
tiddlywebplugins.imaker.egg-info/top_level.txt