Metadata-Version: 1.0
Name: tiddlywebplugins.imaker
Version: 0.1.4
Summary: Make TiddlyWeb instances
Home-page: http://pypi.python.org/pypi/tiddlywebplugins.imaker
Author: Chris Dent
Author-email: cdent@peermore.com
License: UNKNOWN
Platform: Posix; MacOS X; Windows
